{
  "$schema" : "https://json-schema.axonivy.com/14.0-dev/project/data-class.json",
  "simpleName" : "LeaveRequestBusinessDetailsPageData",
  "namespace" : "com.axonivy.portal.developerexamples.customization.sidestep.LeaveRequestBusinessDetailsPage",
  "fields" : [ {
    "name" : "leaveRequestData",
    "type" : "com.axonivy.portal.developerexamples.LeaveRequest"
  }, {
    "name" : "approver",
    "type" : "com.axonivy.portal.components.dto.UserDTO"
  }, {
    "name" : "requester",
    "type" : "com.axonivy.portal.components.dto.UserDTO"
  }, {
    "name" : "caseUuid"
  } ]
}